azex/__init__.py
azex/rates.py
cltjx-0.0.1.dist-info/LICENCE
cltjx-0.0.1.dist-info/METADATA
cltjx-0.0.1.dist-info/WHEEL
cltjx-0.0.1.dist-info/top_level.txt
cltjx-0.0.1.dist-info/RECORD
