Metadata-Version: 2.1
Name: cltjx
Version: 0.0.1
Summary: A small example package
Author: cltj
Author-email: Author <tj@cloudlink.ai>
Project-URL: Homepage, https://github.com/pypa/sampleproject
Project-URL: Bug Tracker, https://github.com/pypa/sampleproject/issues
Classifier: Programming Language :: Python :: 3
Classifier: License :: OSI Approved :: MIT License
Classifier: Operating System :: OS Independent
Requires-Python: >=3.8
License-File: LICENCE
Requires-Dist: requests
Requires-Dist: importlib-metadata ; python_version < "3.8"
